{"12269": {"task": "0_5fHello_5fWorld", "time": 1754895636, "user": "kathycn1223"}, "12370": {"task": "1_5fEcho_5fCompression", "time": 1754896384, "user": "pq106058"}, "12371": {"task": "0_5fHello_5fWorld", "time": 1754896385, "user": "kc_2eryanlee"}, "12372": {"task": "0_5fHello_5fWorld", "time": 1754896392, "user": "chenche_2eyu02"}, "12373": {"task": "1_5fEcho_5fCompression", "time": 1754896395, "user": "1018harris1018"}, "12375": {"task": "1_5fEcho_5fCompression", "time": 1754896414, "user": "brianchiu981226"}, "12376": {"task": "1_5fEcho_5fCompression", "time": 1754896417, "user": "chengweishih945"}, "12377": {"task": "0_5fHello_5fWorld", "time": 1754896441, "user": "kc_2eryanlee"}, "12378": {"task": "2_5fHerbicide", "time": 1754896445, "user": "emmetthor"}, "12379": {"task": "1_5fEcho_5fCompression", "time": 1754896448, "user": "kathycn1223"}, "12400": {"task": "2_5fHerbicide", "time": 1754896767, "user": "chengweishih945"}, "12401": {"task": "1_5fEcho_5fCompression", "time": 1754896807, "user": "james99chi"}, "12406": {"task": "1_5fEcho_5fCompression", "time": 1754896892, "user": "james99chi"}, "12407": {"task": "1_5fEcho_5fCompression", "time": 1754896909, "user": "lllucas0416"}, "12404": {"task": "1_5fEcho_5fCompression", "time": 1754896867, "user": "pohan826"}, "12405": {"task": "0_5fHello_5fWorld", "time": 1754896885, "user": "jimmy20100826"}, "12279": {"task": "0_5fHello_5fWorld", "time": 1754895687, "user": "earlybird2020009"}, "12278": {"task": "0_5fHello_5fWorld", "time": 1754895673, "user": "yp11151035"}, "12271": {"task": "0_5fHello_5fWorld", "time": 1754895639, "user": "1310402"}, "12270": {"task": "0_5fHello_5fWorld", "time": 1754895638, "user": "lllucas0416"}, "12273": {"task": "0_5fHello_5fWorld", "time": 1754895649, "user": "chengweishih945"}, "12272": {"task": "0_5fHello_5fWorld", "time": 1754895648, "user": "lin0411229"}, "12275": {"task": "0_5fHello_5fWorld", "time": 1754895651, "user": "joshluffy99"}, "12274": {"task": "0_5fHello_5fWorld", "time": 1754895649, "user": "diegogamingtw"}, "12277": {"task": "0_5fHello_5fWorld", "time": 1754895663, "user": "jasperteng097"}, "12276": {"task": "0_5fHello_5fWorld", "time": 1754895661, "user": "meps106148"}, "12389": {"task": "1_5fEcho_5fCompression", "time": 1754896601, "user": "melindayeh2011"}, "12388": {"task": "3_5fRainbow_5fPath", "time": 1754896598, "user": "babbrian19"}, "12385": {"task": "2_5fHerbicide", "time": 1754896514, "user": "babbrian19"}, "12384": {"task": "2_5fHerbicide", "time": 1754896503, "user": "joshluffy99"}, "12387": {"task": "1_5fEcho_5fCompression", "time": 1754896558, "user": "frank20100206"}, "12386": {"task": "1_5fEcho_5fCompression", "time": 1754896527, "user": "seantw115"}, "12381": {"task": "0_5fHello_5fWorld", "time": 1754896498, "user": "kc_2eryanlee"}, "12380": {"task": "1_5fEcho_5fCompression", "time": 1754896495, "user": "lllucas0416"}, "12383": {"task": "1_5fEcho_5fCompression", "time": 1754896502, "user": "momo7182"}, "12382": {"task": "1_5fEcho_5fCompression", "time": 1754896500, "user": "earlybird2020009"}, "12305": {"task": "0_5fHello_5fWorld", "time": 1754895840, "user": "chenche_2eyu02"}, "12304": {"task": "0_5fHello_5fWorld", "time": 1754895828, "user": "302004std"}, "12307": {"task": "0_5fHello_5fWorld", "time": 1754895851, "user": "st0111026_2etn"}, "12306": {"task": "0_5fHello_5fWorld", "time": 1754895843, "user": "andre990316"}, "12301": {"task": "0_5fHello_5fWorld", "time": 1754895820, "user": "brian22642664z"}, "12300": {"task": "0_5fHello_5fWorld", "time": 1754895813, "user": "momo7182"}, "12303": {"task": "1_5fEcho_5fCompression", "time": 1754895826, "user": "dcdcdc1031"}, "12302": {"task": "0_5fHello_5fWorld", "time": 1754895822, "user": "aaronliu379"}, "12262": {"task": "0_5fHello_5fWorld", "time": 1754895614, "user": "seantw115"}, "12263": {"task": "0_5fHello_5fWorld", "time": 1754895618, "user": "pq106058"}, "12260": {"task": "0_5fHello_5fWorld", "time": 1754895609, "user": "yp11152061"}, "12261": {"task": "0_5fHello_5fWorld", "time": 1754895614, "user": "dcdcdc1031"}, "12266": {"task": "0_5fHello_5fWorld", "time": 1754895628, "user": "james99chi"}, "12267": {"task": "0_5fHello_5fWorld", "time": 1754895629, "user": "frank20100206"}, "12264": {"task": "0_5fHello_5fWorld", "time": 1754895618, "user": "1121226"}, "12265": {"task": "0_5fHello_5fWorld", "time": 1754895624, "user": "seanwen0525"}, "12398": {"task": "1_5fEcho_5fCompression", "time": 1754896732, "user": "frank20100206"}, "12399": {"task": "1_5fEcho_5fCompression", "time": 1754896734, "user": "lllucas0416"}, "12396": {"task": "2_5fHerbicide", "time": 1754896718, "user": "yp11151035"}, "12397": {"task": "1_5fEcho_5fCompression", "time": 1754896729, "user": "christinepurewang0401"}, "12394": {"task": "0_5fHello_5fWorld", "time": 1754896686, "user": "jimmy20100826"}, "12395": {"task": "2_5fHerbicide", "time": 1754896709, "user": "dcdcdc1031"}, "12392": {"task": "1_5fEcho_5fCompression", "time": 1754896666, "user": "lllucas0416"}, "12393": {"task": "3_5fRainbow_5fPath", "time": 1754896682, "user": "teresa8663"}, "12390": {"task": "1_5fEcho_5fCompression", "time": 1754896646, "user": "pq106058"}, "12391": {"task": "1_5fEcho_5fCompression", "time": 1754896658, "user": "casper15_2etseng"}, "12316": {"task": "0_5fHello_5fWorld", "time": 1754895911, "user": "1018harris1018"}, "12317": {"task": "0_5fHello_5fWorld", "time": 1754895921, "user": "brian22642664z"}, "12314": {"task": "1_5fEcho_5fCompression", "time": 1754895901, "user": "emmetthor"}, "12315": {"task": "0_5fHello_5fWorld", "time": 1754895902, "user": "aaronliu379"}, "12312": {"task": "0_5fHello_5fWorld", "time": 1754895882, "user": "jay723_2etang"}, "12313": {"task": "0_5fHello_5fWorld", "time": 1754895888, "user": "s10830111"}, "12310": {"task": "0_5fHello_5fWorld", "time": 1754895867, "user": "momo7182"}, "12311": {"task": "0_5fHello_5fWorld", "time": 1754895871, "user": "chenche_2eyu02"}, "12318": {"task": "1_5fEcho_5fCompression", "time": 1754895925, "user": "jasperteng097"}, "12319": {"task": "0_5fHello_5fWorld", "time": 1754895929, "user": "lin0411229"}, "12309": {"task": "0_5fHello_5fWorld", "time": 1754895860, "user": "302004std"}, "12308": {"task": "1_5fEcho_5fCompression", "time": 1754895858, "user": "jasperteng097"}, "12323": {"task": "0_5fHello_5fWorld", "time": 1754895953, "user": "andre990316"}, "12402": {"task": "3_5fRainbow_5fPath", "time": 1754896822, "user": "teresa8663"}, "12321": {"task": "1_5fEcho_5fCompression", "time": 1754895941, "user": "babbrian19"}, "12320": {"task": "0_5fHello_5fWorld", "time": 1754895933, "user": "1130446"}, "12327": {"task": "0_5fHello_5fWorld", "time": 1754895996, "user": "chenche_2eyu02"}, "12326": {"task": "0_5fHello_5fWorld", "time": 1754895987, "user": "evelyn_2ek_2ey_2eliu"}, "12325": {"task": "1_5fEcho_5fCompression", "time": 1754895981, "user": "brianchiu981226"}, "12324": {"task": "0_5fHello_5fWorld", "time": 1754895974, "user": "aaronliu379"}, "12329": {"task": "1_5fEcho_5fCompression", "time": 1754896025, "user": "meps106148"}, "12328": {"task": "0_5fHello_5fWorld", "time": 1754896000, "user": "pohan826"}, "12338": {"task": "0_5fHello_5fWorld", "time": 1754896093, "user": "chenche_2eyu02"}, "12339": {"task": "1_5fEcho_5fCompression", "time": 1754896096, "user": "st0111026_2etn"}, "12334": {"task": "0_5fHello_5fWorld", "time": 1754896054, "user": "lin0411229"}, "12335": {"task": "1_5fEcho_5fCompression", "time": 1754896066, "user": "diegogamingtw"}, "12336": {"task": "0_5fHello_5fWorld", "time": 1754896088, "user": "yp11251060"}, "12337": {"task": "1_5fEcho_5fCompression", "time": 1754896091, "user": "seanwen0525"}, "12330": {"task": "1_5fEcho_5fCompression", "time": 1754896031, "user": "wudajy670910"}, "12331": {"task": "0_5fHello_5fWorld", "time": 1754896043, "user": "chenche_2eyu02"}, "12332": {"task": "0_5fHello_5fWorld", "time": 1754896045, "user": "yp11251060"}, "12333": {"task": "0_5fHello_5fWorld", "time": 1754896050, "user": "peishunwu0313"}, "12403": {"task": "2_5fHerbicide", "time": 1754896831, "user": "chengweishih945"}, "12349": {"task": "0_5fHello_5fWorld", "time": 1754896186, "user": "chenche_2eyu02"}, "12348": {"task": "0_5fHello_5fWorld", "time": 1754896166, "user": "andre990316"}, "12341": {"task": "1_5fEcho_5fCompression", "time": 1754896115, "user": "1310402"}, "12340": {"task": "1_5fEcho_5fCompression", "time": 1754896101, "user": "kathycn1223"}, "12343": {"task": "0_5fHello_5fWorld", "time": 1754896130, "user": "casper15_2etseng"}, "12342": {"task": "2_5fHerbicide", "time": 1754896127, "user": "emmetthor"}, "12345": {"task": "0_5fHello_5fWorld", "time": 1754896146, "user": "christinepurewang0401"}, "12344": {"task": "1_5fEcho_5fCompression", "time": 1754896140, "user": "chenche_2eyu02"}, "12347": {"task": "0_5fHello_5fWorld", "time": 1754896161, "user": "s10830111"}, "12346": {"task": "1_5fEcho_5fCompression", "time": 1754896156, "user": "112041"}, "12299": {"task": "0_5fHello_5fWorld", "time": 1754895802, "user": "frank20100206"}, "12298": {"task": "0_5fHello_5fWorld", "time": 1754895799, "user": "chenche_2eyu02"}, "12322": {"task": "0_5fHello_5fWorld", "time": 1754895950, "user": "1018harris1018"}, "12293": {"task": "0_5fHello_5fWorld", "time": 1754895774, "user": "babbrian19"}, "12292": {"task": "1_5fEcho_5fCompression", "time": 1754895770, "user": "joshluffy99"}, "12291": {"task": "0_5fHello_5fWorld", "time": 1754895749, "user": "frank20100206"}, "12290": {"task": "0_5fHello_5fWorld", "time": 1754895747, "user": "yp11152070"}, "12297": {"task": "0_5fHello_5fWorld", "time": 1754895788, "user": "wudajy670910"}, "12296": {"task": "1_5fEcho_5fCompression", "time": 1754895785, "user": "1121226"}, "12295": {"task": "1_5fEcho_5fCompression", "time": 1754895783, "user": "jay723_2etang"}, "12294": {"task": "0_5fHello_5fWorld", "time": 1754895781, "user": "momo7182"}, "12358": {"task": "1_5fEcho_5fCompression", "time": 1754896261, "user": "112041"}, "12359": {"task": "1_5fEcho_5fCompression", "time": 1754896268, "user": "chengweishih945"}, "12352": {"task": "1_5fEcho_5fCompression", "time": 1754896209, "user": "brianchiu981226"}, "12353": {"task": "0_5fHello_5fWorld", "time": 1754896221, "user": "chenche_2eyu02"}, "12350": {"task": "1_5fEcho_5fCompression", "time": 1754896198, "user": "andre990316"}, "12351": {"task": "1_5fEcho_5fCompression", "time": 1754896199, "user": "kc_2eryanlee"}, "12356": {"task": "0_5fHello_5fWorld", "time": 1754896252, "user": "andre990316"}, "12354": {"task": "0_5fHello_5fWorld", "time": 1754896224, "user": "112041"}, "12355": {"task": "0_5fHello_5fWorld", "time": 1754896245, "user": "brian22642664z"}, "12268": {"task": "0_5fHello_5fWorld", "time": 1754895630, "user": "teresa8663"}, "12284": {"task": "0_5fHello_5fWorld", "time": 1754895703, "user": "lin0411229"}, "12285": {"task": "0_5fHello_5fWorld", "time": 1754895711, "user": "emmetthor"}, "12286": {"task": "0_5fHello_5fWorld", "time": 1754895720, "user": "babbrian19"}, "12287": {"task": "0_5fHello_5fWorld", "time": 1754895726, "user": "pq106058"}, "12280": {"task": "0_5fHello_5fWorld", "time": 1754895691, "user": "melindayeh2011"}, "12281": {"task": "0_5fHello_5fWorld", "time": 1754895692, "user": "yp11251060"}, "12282": {"task": "0_5fHello_5fWorld", "time": 1754895693, "user": "brianchiu981226"}, "12283": {"task": "0_5fHello_5fWorld", "time": 1754895700, "user": "brianweihuang"}, "12288": {"task": "0_5fHello_5fWorld", "time": 1754895729, "user": "kc_2eryanlee"}, "12289": {"task": "1_5fEcho_5fCompression", "time": 1754895746, "user": "teresa8663"}, "12367": {"task": "1_5fEcho_5fCompression", "time": 1754896339, "user": "frank20100206"}, "12366": {"task": "1_5fEcho_5fCompression", "time": 1754896335, "user": "peishunwu0313"}, "12365": {"task": "0_5fHello_5fWorld", "time": 1754896330, "user": "chenche_2eyu02"}, "12364": {"task": "1_5fEcho_5fCompression", "time": 1754896327, "user": "lllucas0416"}, "12363": {"task": "2_5fHerbicide", "time": 1754896318, "user": "babbrian19"}, "12362": {"task": "1_5fEcho_5fCompression", "time": 1754896308, "user": "earlybird2020009"}, "12361": {"task": "1_5fEcho_5fCompression", "time": 1754896298, "user": "yp11251060"}, "12360": {"task": "1_5fEcho_5fCompression", "time": 1754896283, "user": "aaronliu379"}, "12369": {"task": "1_5fEcho_5fCompression", "time": 1754896357, "user": "evelyn_2ek_2ey_2eliu"}, "12368": {"task": "1_5fEcho_5fCompression", "time": 1754896349, "user": "brianweihuang"}}